snipserve_cli/__init__.py
snipserve_cli/api.py
snipserve_cli/cli.py
snipserve_cli/config.py
snipserve_cli/utils.py
snipserve_cli-1.0.0.dist-info/METADATA
snipserve_cli-1.0.0.dist-info/WHEEL
snipserve_cli-1.0.0.dist-info/entry_points.txt
snipserve_cli-1.0.0.dist-info/top_level.txt
snipserve_cli-1.0.0.dist-info/RECORD
