Metadata-Version: 2.4
Name: snipserve-cli
Version: 1.0.0
Summary: Command-line interface for SnipServe paste service
Home-page: https://github.com/spkal01/snipserve-cli
Author: Spkal01
Author-email: spkal01 <kalligeross@gmail.com>
License-Expression: MIT
Project-URL: Homepage, https://github.com/spkal01/snipserve-cli
Project-URL: Bug Reports, https://github.com/spkal01/snipserve-cli/issues
Project-URL: Source Code, https://github.com/spkal01/snipserve-cli
Keywords: paste,pastebin,cli,snippets,code-sharing
Classifier: Development Status :: 4 - Beta
Classifier: Intended Audience :: Developers
Classifier: Operating System :: OS Independent
Classifier: Programming Language :: Python :: 3
Classifier: Programming Language :: Python :: 3.7
Classifier: Programming Language :: Python :: 3.8
Classifier: Programming Language :: Python :: 3.9
Classifier: Programming Language :: Python :: 3.10
Classifier: Programming Language :: Python :: 3.11
Requires-Python: >=3.7
Requires-Dist: click>=8.0.0
Requires-Dist: requests>=2.25.0
Dynamic: author
Dynamic: home-page
Dynamic: requires-python
